[{"meta":{"filename":"Field.svelte","lineno":6,"columnno":2,"path":"src/components"},"description":"Label for input","type":["String"],"optional":true,"name":"label","_isSvelteDoc":true,"_svelteProps":{"type":{"names":["String"]},"optional":true,"name":"label"},"kind":"prop","longname":"module:Field~label","scope":"inner","memberof":"module:Field","___s":true,"values":""},{"meta":{"filename":"Field.svelte","lineno":11,"columnno":2,"path":"src/components"},"description":"Type (color of control)","type":["String"],"optional":true,"name":"type","_isSvelteDoc":true,"_svelteProps":{"type":{"names":["String"]},"optional":true,"name":"type"},"kind":"prop","values":"<code>is-white</code>, <code>is-black</code>, <code>is-light</code>, <code>is-dark</code>, <code>is-primary</code>, <code>is-info</code>, <code>is-success</code>, <code>is-warning</code>, <code>is-danger</code>","longname":"module:Field~type","scope":"inner","memberof":"module:Field","___s":true},{"meta":{"filename":"Field.svelte","lineno":17,"columnno":2,"path":"src/components"},"description":"Message to show beneath input","type":["String"],"optional":true,"name":"message","_isSvelteDoc":true,"_svelteProps":{"type":{"names":["String"]},"optional":true,"name":"message"},"kind":"prop","longname":"module:Field~message","scope":"inner","memberof":"module:Field","___s":true,"values":""}]